irbt/__init__.py
irbt/cloud.py
irbt/logger.py
irbt/parse_command_line.py
irbt/robot.py
irbt-0.14.0.data/scripts/irbt-cli.py
tests/__init__.py
tests/cloud_mock.py
tests/conftest.py
tests/test_cloud.py
tests/test_robot.py
usr/local/etc/aws-root-ca1.cer
irbt-0.14.0.dist-info/LICENSE
irbt-0.14.0.dist-info/METADATA
irbt-0.14.0.dist-info/WHEEL
irbt-0.14.0.dist-info/top_level.txt
irbt-0.14.0.dist-info/RECORD
