Metadata-Version: 2.1
Name: irbt
Version: 0.14.0
Summary: A Library to interact with irbt appliances
Home-page: https://github.com/tidalf/irbt
Author: D@korp
Author-email: tidalf@ematome.com
License: UNKNOWN
Platform: UNKNOWN
Classifier: Programming Language :: Python :: 3
Classifier: License :: OSI Approved :: MIT License
Classifier: Operating System :: OS Independent
Requires-Python: >=3.6
Requires-Dist: aws-requests-auth
Requires-Dist: AWSIoTPythonSDK
